plagdef/__init__.py
plagdef/app.py
plagdef/config/app.ini
plagdef/config/logging.ini
plagdef/config.py
plagdef/gui/__init__.py
plagdef/gui/controllers.py
plagdef/gui/main.py
plagdef/gui/model.py
plagdef/gui/res/add_circle_orange.png
plagdef/gui/res/add_circle_white.png
plagdef/gui/res/before_white.png
plagdef/gui/res/common.svg
plagdef/gui/res/common_white.png
plagdef/gui/res/compile_resources.bat
plagdef/gui/res/done_circle_white.png
plagdef/gui/res/error_white.png
plagdef/gui/res/folder_open_white.png
plagdef/gui/res/ger_flag.png
plagdef/gui/res/icon.ico
plagdef/gui/res/inbox_white.png
plagdef/gui/res/lang_white.png
plagdef/gui/res/loading.gif
plagdef/gui/res/logo.png
plagdef/gui/res/next_white.png
plagdef/gui/res/open_white.png
plagdef/gui/res/plagiarism_white.png
plagdef/gui/res/resources.qrc
plagdef/gui/res/search_white.png
plagdef/gui/res/settings_white.png
plagdef/gui/res/uk_flag.png
plagdef/gui/resources.py
plagdef/gui/ui/error_widget.ui
plagdef/gui/ui/home_widget.ui
plagdef/gui/ui/loading_widget.ui
plagdef/gui/ui/main_window.ui
plagdef/gui/ui/matches_dialog.ui
plagdef/gui/ui/msg_dialog.ui
plagdef/gui/ui/no_results_widget.ui
plagdef/gui/ui/results_widget.ui
plagdef/gui/ui/settings_dialog.ui
plagdef/gui/views.py
plagdef/model/__init__.py
plagdef/model/detection.py
plagdef/model/download.py
plagdef/model/matching.py
plagdef/model/models.py
plagdef/model/pipeline/__init__.py
plagdef/model/pipeline/doc_translate.py
plagdef/model/pipeline/extension.py
plagdef/model/pipeline/filtering.py
plagdef/model/pipeline/preprocessing.py
plagdef/model/pipeline/seeding.py
plagdef/model/pipeline/translate.py
plagdef/model/reporting.py
plagdef/model/stopwords.py
plagdef/repositories.py
plagdef/res/DejaVuSansCondensed.ttf
plagdef/services.py
plagdef/util.py
plagdef-1.5.3.dist-info/LICENSE
plagdef-1.5.3.dist-info/METADATA
plagdef-1.5.3.dist-info/WHEEL
plagdef-1.5.3.dist-info/entry_points.txt
plagdef-1.5.3.dist-info/RECORD
