Metadata-Version: 2.3
Name: plagdef
Version: 1.5.3
Summary: A tool which makes life hard for students who try to make theirs simple.
License: GPL-3.0-or-later
Author: Yannik Queisler
Requires-Python: >=3.10,<3.11
Classifier: Development Status :: 4 - Beta
Classifier: Intended Audience :: Developers
Classifier: License :: OSI Approved :: GNU General Public License v3 or later (GPLv3+)
Classifier: Operating System :: OS Independent
Classifier: Programming Language :: Python :: 3
Classifier: Programming Language :: Python :: 3.10
Requires-Dist: PyPDF2 (>=3.0.1,<4.0.0)
Requires-Dist: Werkzeug (>=3.1.3,<4.0.0)
Requires-Dist: beautifulsoup4 (>=4.13.4,<5.0.0)
Requires-Dist: click (>=8.2.1,<9.0.0)
Requires-Dist: deep-translator (>=1.11.4,<2.0.0)
Requires-Dist: fpdf2 (>=2.8.3,<3.0.0)
Requires-Dist: jsonpickle (>=4.1.1,<5.0.0)
Requires-Dist: langdetect (>=1.0.9,<2.0.0)
Requires-Dist: networkx (>=3.4.2,<4.0.0)
Requires-Dist: numpy (>=1.26.4,<2.0.0)
Requires-Dist: ocrmypdf (>=16.10.4,<17.0.0)
Requires-Dist: pdfplumber (>=0.11.7,<0.12.0)
Requires-Dist: pyside6 (>=6.4,<6.5)
Requires-Dist: python-magic (>=0.4.27,<0.5.0)
Requires-Dist: selenium (>=4.34.2,<5.0.0)
Requires-Dist: sortedcontainers (>=2.4.0,<3.0.0)
Requires-Dist: stanza (>=1.9,<1.10)
Requires-Dist: torch (>=2.5,<2.6)
Requires-Dist: tqdm (>=4.67.1,<5.0.0)
Requires-Dist: urlextract (>=1.9.0,<2.0.0)
Requires-Dist: webdriver-manager (>=4.0.2,<5.0.0)
Project-URL: Homepage, https://github.com/devWhyqueue/plagdef
